README.md
setup.py
pltCIreg/__init__.py
pltCIreg/pltCIreg.py
pltCIreg.egg-info/PKG-INFO
pltCIreg.egg-info/SOURCES.txt
pltCIreg.egg-info/dependency_links.txt
pltCIreg.egg-info/top_level.txt