Metadata-Version: 1.0
Name: pltCIreg
Version: 0.0.7
Summary: 提供画对比折线图，且附带置信区间的接口
Home-page: https://github.com/zhengz3000/pltCIreg
Author: Aldrich_1
Author-email: zhengz3000@gmail.com
License: UNKNOWN
Platform: UNKNOWN
